st_soccer/__init__.py
st_soccer/example.py
st_soccer/frontend/build/asset-manifest.json
st_soccer/frontend/build/bootstrap.min.css
st_soccer/frontend/build/index.html
st_soccer/frontend/build/static/js/main.9f476ea9.js
st_soccer/frontend/build/static/js/main.9f476ea9.js.LICENSE.txt
st_soccer/frontend/build/static/js/main.9f476ea9.js.map
st_soccer/frontend/build/static/js/main.f77417c8.js
st_soccer/frontend/build/static/js/main.f77417c8.js.LICENSE.txt
st_soccer/frontend/build/static/js/main.f77417c8.js.map
streamlit_soccer-0.0.1.dist-info/METADATA
streamlit_soccer-0.0.1.dist-info/WHEEL
streamlit_soccer-0.0.1.dist-info/top_level.txt
streamlit_soccer-0.0.1.dist-info/RECORD
