Metadata-Version: 2.1
Name: streamlit-soccer
Version: 0.0.1
Summary: UNKNOWN
Home-page: UNKNOWN
Author: Devin Pleuler
Author-email: 
License: UNKNOWN
Platform: UNKNOWN
Requires-Python: >=3.6
Requires-Dist: streamlit>=0.66
Requires-Dist: kloppy
Provides-Extra: devel
Requires-Dist: wheel; extra == "devel"
Requires-Dist: pytest==7.4.0; extra == "devel"
Requires-Dist: playwright==1.48.0; extra == "devel"
Requires-Dist: requests==2.31.0; extra == "devel"
Requires-Dist: pytest-playwright-snapshot==1.0; extra == "devel"
Requires-Dist: pytest-rerunfailures==12.0; extra == "devel"
